{"changelog.md":"C_9hIsHi","documentation_collection_aggregation.md":"BVB4MDqG","documentation_collection_analyse-schema.md":"Cq60QFUJ","documentation_collection_index.md":"96r6xX33","documentation_collection_pagination.md":"DSMAgXFs","documentation_database_bson.md":"NkCKGCUj","documentation_database_config.md":"C5u9OiCV","documentation_database_index.md":"DsDBPx04","documentation_database_lucene.md":"B6kElqCE","documentation_database_provider.md":"BA72hjOn","documentation_database_reactive-streams.md":"0-XFJuAH","documentation_database_relationships.md":"BdJlKmWE","documentation_getting-started.md":"Bm0pCNuW","documentation_gridfs-dao_crud.md":"CjFOi_dv","documentation_gridfs-dao_index.md":"MG2vKDkL","documentation_gridfs-dao_metadata.md":"DA2PHPiJ","documentation_local-server.md":"yuNlxhTW","documentation_mongo-dao_base.md":"BiswgD6x","documentation_mongo-dao_crud.md":"Cnd4Lc-a","documentation_mongo-dao_index.md":"yyghSsyU","documentation_mongo-dao_search.md":"CXMfqpfW","documentation_sql_index.md":"hT8A36dA","documentation_sql_jdbc-driver.md":"DDxSgC-4","documentation_sql_queryholder.md":"CXGsxwHe","index.md":"D09noATB"}
